[
  {
    "title": "Application Quality",
    "description": "Inference of application quality from encrypted traffic.",
    "image": {
      "url": "images/features/noun_branding_1885335.svg",
      "width": 80,
      "height": 80
    }
  },
  {
    "title": "Performance Measurement",
    "description": "Visualize and monitor traffic patterns from your users and devices.",
    "image": {
      "url": "images/features/noun_The Process_1885341.svg",
      "width": 80,
      "height": 80
    }
  },
  {
    "title": "Encrypted Traffic Inference",
    "description": "Inference of application quality from encrypted traffic.",
    "image": {
      "url": "images/features/noun_3d modeling_1885342.svg",
      "width": 80,
      "height": 80
    }
  }
]
